CHANGES.rst
COPYING
COPYING.LESSER
MANIFEST.in
Makefile
README.rst
bootstrap-buildout.py
bootstrap-virtualenv.in
bootstrap-virtualenv.py
buildout.cfg
ez_setup.py
requirements-app.in
requirements-dev.in
requirements-dev.txt
requirements-test.in
requirements.txt
setup.cfg
setup.py
tox.ini
docs/.gitignore
docs/Makefile
docs/make.bat
docs/source/conf.py
docs/source/index.rst
docs/source/_static/.gitignore
mete0r.distutils.virtualenv.egg-info/PKG-INFO
mete0r.distutils.virtualenv.egg-info/SOURCES.txt
mete0r.distutils.virtualenv.egg-info/dependency_links.txt
mete0r.distutils.virtualenv.egg-info/entry_points.txt
mete0r.distutils.virtualenv.egg-info/not-zip-safe
mete0r.distutils.virtualenv.egg-info/requires.txt
mete0r.distutils.virtualenv.egg-info/top_level.txt
mete0r_distutils_virtualenv/__init__.py
mete0r_distutils_virtualenv/commands.py
mete0r_distutils_virtualenv/tests/__init__.py
mete0r_distutils_virtualenv/tests/test_app.py