Metadata-Version: 1.1
Name: mete0r.distutils.virtualenv
Version: 0.0.2
Summary: Manage virtualenvs with requirement files
Home-page: https://github.com/mete0r/mete0r.distutils.virtualenv
Author: mete0r
Author-email: mete0r@sarangbang.or.kr
License: GNU Lesser General Public License v3 or later (LGPLv3+)
Keywords: distutils,virtualenv
Platform: UNKNOWN
Classifier: Development Status :: 3 - Alpha
Classifier: License :: OSI Approved :: GNU Lesser General Public License v3 or later (LGPLv3+)
Classifier: Programming Language :: Python :: 2.7
Classifier: Programming Language :: Python :: Implementation :: CPython
